{"format":1,"version":"4.5.3","settings":"7b9430cf68fc8014d03eddeee6e873be","files":{"project___init___py":{"hash":"50bf96438c3d33f7da7949d6f603c108","index":{"nums":[1,14,0,6,0,0,0],"html_filename":"project___init___py.html","relative_filename":"project/__init__.py"}},"project_api_evs_py":{"hash":"6ccaeed461a04618853f8f131f436fdc","index":{"nums":[1,61,0,0,10,0,0],"html_filename":"project_api_evs_py.html","relative_filename":"project/api/evs.py"}},"project_api_models_py":{"hash":"0a9005ecc186e94b0cc26133b9a35366","index":{"nums":[1,43,0,36,4,2,2],"html_filename":"project_api_models_py.html","relative_filename":"project/api/models.py"}}}}